pt_br_verbs_lemmatizer/__init__.py
pt_br_verbs_lemmatizer/main.py
pt_br_verbs_lemmatizer/dataset/dic_duplicated_flex_verbs.msgpack
pt_br_verbs_lemmatizer/dataset/dic_pt_br_verbs_lemma.msgpack
pt_br_verbs_lemmatizer-0.1.7.dist-info/METADATA
pt_br_verbs_lemmatizer-0.1.7.dist-info/WHEEL
pt_br_verbs_lemmatizer-0.1.7.dist-info/top_level.txt
pt_br_verbs_lemmatizer-0.1.7.dist-info/RECORD
