Metadata-Version: 2.1
Name: pt_br_verbs_lemmatizer
Version: 0.1.7
Summary: Program designed to lemmatize the various verbal inflections present in the Brazilian Portuguese language quickly and efficiently.
Author: Igor Caetano de Souza
Project-URL: GitHub Repository, https://github.com/IgorCaetano/pt_br_verbs_lemmatizer
Requires-Dist: msgpack ==1.0.7
